cjm_fasthtml_settings/__init__.py
cjm_fasthtml_settings/_modidx.py
cjm_fasthtml_settings/routes.py
cjm_fasthtml_settings/components/__init__.py
cjm_fasthtml_settings/components/forms.py
cjm_fasthtml_settings/components/master_detail_adapter.py
cjm_fasthtml_settings/core/__init__.py
cjm_fasthtml_settings/core/config.py
cjm_fasthtml_settings/core/html_ids.py
cjm_fasthtml_settings/core/schema_group.py
cjm_fasthtml_settings/core/schemas.py
cjm_fasthtml_settings/core/utils.py
cjm_fasthtml_settings-0.0.16.dist-info/licenses/LICENSE
cjm_fasthtml_settings-0.0.16.dist-info/METADATA
cjm_fasthtml_settings-0.0.16.dist-info/WHEEL
cjm_fasthtml_settings-0.0.16.dist-info/entry_points.txt
cjm_fasthtml_settings-0.0.16.dist-info/top_level.txt
cjm_fasthtml_settings-0.0.16.dist-info/RECORD
