Metadata-Version: 2.4
Name: cjm-fasthtml-settings
Version: 0.0.16
Summary: A drop-in schema-based configuration system for FastHTML applications with automatic UI generation, sidebar navigation, and persistent storage.
Home-page: https://github.com/cj-mills/cjm-fasthtml-settings
Author: Christian J. Mills
Author-email: 9126128+cj-mills@users.noreply.github.com
License: Apache Software License 2.0
Keywords: nbdev jupyter notebook python
Classifier: Development Status :: 4 - Beta
Classifier: Intended Audience :: Developers
Classifier: Natural Language :: English
Classifier: Programming Language :: Python :: 3.9
Classifier: Programming Language :: Python :: 3.10
Classifier: Programming Language :: Python :: 3.11
Classifier: Programming Language :: Python :: 3.12
Classifier: License :: OSI Approved :: Apache Software License
Requires-Python: >=3.9
License-File: LICENSE
Requires-Dist: fastcore
Requires-Dist: pandas
Requires-Dist: cjm_fasthtml_daisyui
Requires-Dist: cjm_fasthtml_jsonschema
Requires-Dist: cjm_fasthtml_app_core
Requires-Dist: cjm_error_handling
Requires-Dist: cjm_fasthtml_interactions
Provides-Extra: dev
Dynamic: author
Dynamic: author-email
Dynamic: classifier
Dynamic: description
Dynamic: description-content-type
Dynamic: home-page
Dynamic: keywords
Dynamic: license
Dynamic: license-file
Dynamic: provides-extra
Dynamic: requires-dist
Dynamic: requires-python
Dynamic: summary
